mpubsub/__init__.py
mpubsub/broker.py
mpubsub/net.py
mpubsub/typing.py
mpubsub-0.0.1.dist-info/LICENSE
mpubsub-0.0.1.dist-info/WHEEL
mpubsub-0.0.1.dist-info/METADATA
mpubsub-0.0.1.dist-info/RECORD
